LICENSE
MANIFEST.in
README.md
requirements.txt
setup.py
dropsonde/__init__.py
dropsonde/__version__.py
dropsonde/util.py
dropsonde.egg-info/PKG-INFO
dropsonde.egg-info/SOURCES.txt
dropsonde.egg-info/dependency_links.txt
dropsonde.egg-info/requires.txt
dropsonde.egg-info/top_level.txt
dropsonde/pb/__init__.py
dropsonde/pb/envelope_pb2.py
dropsonde/pb/error_pb2.py
dropsonde/pb/http_pb2.py
dropsonde/pb/log_pb2.py
dropsonde/pb/metric_pb2.py
dropsonde/pb/uuid_pb2.py