Metadata-Version: 1.0
Name: dropsonde
Version: 0.0.3
Summary: Compiled python generated from the Cloud Foundry Dropsonde Protobuf definition files
Home-page: https://github.com/hsdp/python-dropsonde
Author: Adam Jaso
Author-email: UNKNOWN
License: Apache License Version 2.0
Platform: UNKNOWN
